django_tbank_kassa/__init__.py
django_tbank_kassa/admin.py
django_tbank_kassa/apps.py
django_tbank_kassa/checks.py
django_tbank_kassa/generics.py
django_tbank_kassa/migrations/0001_initial.py
django_tbank_kassa/migrations/__init__.py
django_tbank_kassa/mixins.py
django_tbank_kassa/models.py
django_tbank_kassa/serializers.py
django_tbank_kassa/services.py
django_tbank_kassa/settings.py
django_tbank_kassa-0.1.1.dist-info/METADATA
django_tbank_kassa-0.1.1.dist-info/WHEEL
django_tbank_kassa-0.1.1.dist-info/RECORD
