Metadata-Version: 2.3
Name: django-tbank-kassa
Version: 0.1.1
Summary: 
Author: Rostislaww
Author-email: rostiki.com@mail.ru
Requires-Python: >=3.11,<4.0
Classifier: Programming Language :: Python :: 3
Classifier: Programming Language :: Python :: 3.11
Classifier: Programming Language :: Python :: 3.12
Classifier: Programming Language :: Python :: 3.13
Requires-Dist: django (>=5.0.1,<6.0.0)
Requires-Dist: djangorestframework (>=3.15.2,<4.0.0)
Requires-Dist: tbank-kassa (>=0.3.3,<0.4.0)
Project-URL: Homepage, https://github.com/RostHarcha/django-tbank-kassa
